MANIFEST.in
README.rst
setup.cfg
setup.py
bnrml/__init__.py
bnrml/cli.py
bnrml/errors.py
bnrml/mappings.py
bnrml/normalizers.py
bnrml/version.py
bnrml.egg-info/PKG-INFO
bnrml.egg-info/SOURCES.txt
bnrml.egg-info/dependency_links.txt
bnrml.egg-info/entry_points.txt
bnrml.egg-info/requires.txt
bnrml.egg-info/top_level.txt
bnrml/soundalike/__init__.py
bnrml/soundalike/distance.py
bnrml/soundalike/encoding.py
bnrml/soundalike/normalizers.py