Metadata-Version: 1.2
Name: bnrml
Version: 0.0.2
Summary: Be normal! (It's a string normalization framework.)
Home-page: https://github.com/patdaburu/bnrml
Author: Pat Daburu
Author-email: pat@daburu.net
License: MIT
Download-URL: https://github.com/patdaburu/bnrml/archive/0.0.2.tar.gz
Platform: UNKNOWN
Classifier: Development Status :: 3 - Alpha
Classifier: Intended Audience :: Developers
Classifier: Topic :: Software Development :: Libraries
Classifier: License :: OSI Approved :: MIT License
Classifier: Programming Language :: Python :: 3.6
Requires-Python: >=0.0.1
